quantumcatch/__init__.py
quantumcatch/fitting_tools.py
quantumcatch/simulation.py
quantumcatch/simulation_jax.py
quantumcatch/telegraph_noise_tools.py
quantumcatch-0.2.5.dist-info/METADATA
quantumcatch-0.2.5.dist-info/WHEEL
quantumcatch-0.2.5.dist-info/licenses/LICENSE
quantumcatch-0.2.5.dist-info/RECORD
