Metadata-Version: 2.4
Name: QuantumCatch
Version: 0.2.5
Summary: Package for the simulation and evaluation of continuous quantum measurements
Project-URL: Homepage, https://github.com/MarkusSifft/QuantumCatch
Project-URL: Bug Tracker, https://github.com/MarkusSifft/QuantumCatch/issues
Author-email: Markus Sifft <markus.sifft@rub.de>
License-File: LICENSE
Keywords: analysis,continuous quantum measurement,quantum measurement,quantum polyspectra,signal processing,spectra
Classifier: Development Status :: 2 - Pre-Alpha
Classifier: Intended Audience :: Science/Research
Classifier: License :: OSI Approved :: BSD License
Classifier: Operating System :: MacOS
Classifier: Operating System :: Microsoft :: Windows
Classifier: Operating System :: POSIX
Classifier: Operating System :: Unix
Classifier: Programming Language :: Python
Classifier: Programming Language :: Python :: 3
Classifier: Topic :: Scientific/Engineering
Requires-Python: >=3.7
Requires-Dist: arrayfire
Requires-Dist: cachetools
Requires-Dist: h5py
Requires-Dist: ipywidgets
Requires-Dist: lmfit
Requires-Dist: matplotlib
Requires-Dist: numba
Requires-Dist: numpy
Requires-Dist: pandas
Requires-Dist: plotly
Requires-Dist: psutil
Requires-Dist: qutip<=4.7.5
Requires-Dist: scipy==1.12.0
Requires-Dist: signalsnap
Requires-Dist: tqdm
